ggsci/__init__.py
ggsci/data.py
ggsci/data_iterm.py
ggsci/examples.py
ggsci/palettes.py
ggsci/scales.py
ggsci/utils.py
ggsci-1.1.0.dist-info/METADATA
ggsci-1.1.0.dist-info/WHEEL
ggsci-1.1.0.dist-info/licenses/LICENSE
ggsci-1.1.0.dist-info/RECORD
